LICENSE.txt
README.md
setup.cfg
setup.py
certbot_dns_do/__init__.py
certbot_dns_do/dns_do.py
certbot_dns_do.egg-info/PKG-INFO
certbot_dns_do.egg-info/SOURCES.txt
certbot_dns_do.egg-info/dependency_links.txt
certbot_dns_do.egg-info/entry_points.txt
certbot_dns_do.egg-info/requires.txt
certbot_dns_do.egg-info/top_level.txt